aiowinrm/__init__.py
aiowinrm/_version.py
aiowinrm/api.py
aiowinrm/constants.py
aiowinrm/core.py
aiowinrm/errors.py
aiowinrm/sync.py
aiowinrm/utils.py
aiowinrm/soap/__init__.py
aiowinrm/soap/header.py
aiowinrm/soap/namespaces.py
aiowinrm/soap/protocol.py
aiowinrm-0.0.1.dist-info/DESCRIPTION.rst
aiowinrm-0.0.1.dist-info/METADATA
aiowinrm-0.0.1.dist-info/RECORD
aiowinrm-0.0.1.dist-info/WHEEL
aiowinrm-0.0.1.dist-info/metadata.json
aiowinrm-0.0.1.dist-info/top_level.txt
